{"chunk_definitions":[{"chunk_id":"cbougb9l3qzwq","chunk_label":"unnamed-chunk-1","document_id":"95E990B3","expansion_state":0,"options":{"engine":"r","label":"unnamed-chunk-2"},"row":9,"row_count":1,"visible":true},{"chunk_id":"ck1oz11hslfk2","chunk_label":"unnamed-chunk-3","document_id":"95E990B3","expansion_state":0,"options":{"engine":"r","label":"unnamed-chunk-4"},"row":31,"row_count":1,"visible":true},{"chunk_id":"cxtmge0jwfvhl","chunk_label":"unnamed-chunk-4","document_id":"95E990B3","expansion_state":0,"options":{"engine":"r","label":"unnamed-chunk-6"},"row":53,"row_count":1,"visible":true},{"chunk_id":"cygu1166qbj0z","chunk_label":"unnamed-chunk-5","document_id":"95E990B3","expansion_state":0,"options":{"engine":"r","label":"unnamed-chunk-8"},"row":70,"row_count":1,"visible":true},{"chunk_id":"cigzurbfxm6r2","chunk_label":"unnamed-chunk-6","document_id":"95E990B3","expansion_state":0,"options":{"engine":"r","label":"unnamed-chunk-1"},"row":75,"row_count":1,"visible":true},{"chunk_id":"cfwfftcczk9o1","chunk_label":"unnamed-chunk-7","document_id":"95E990B3","expansion_state":0,"options":{"engine":"r","label":"unnamed-chunk-2"},"row":87,"row_count":1,"visible":true},{"chunk_id":"c1bjp4mni87s0","chunk_label":"unnamed-chunk-8","document_id":"95E990B3","expansion_state":0,"options":{"engine":"r","label":"unnamed-chunk-1"},"row":120,"row_count":1,"visible":true},{"chunk_id":"ctzhl1oe1xu7k","chunk_label":"unnamed-chunk-9","document_id":"95E990B3","expansion_state":0,"options":{"engine":"r","label":"unnamed-chunk-1"},"row":141,"row_count":1,"visible":true},{"chunk_id":"cj2ekc1qt7on0","chunk_label":"unnamed-chunk-10","document_id":"95E990B3","expansion_state":0,"options":{"engine":"r","label":"unnamed-chunk-1"},"row":147,"row_count":1,"visible":true},{"chunk_id":"ca852rspbi4co","chunk_label":"unnamed-chunk-11","document_id":"95E990B3","expansion_state":0,"options":{"engine":"r","label":"unnamed-chunk-1"},"row":154,"row_count":1,"visible":true},{"chunk_id":"c8zfaf185i0qc","chunk_label":"unnamed-chunk-12","document_id":"95E990B3","expansion_state":0,"options":{"engine":"r","label":"unnamed-chunk-1"},"row":185,"row_count":1,"visible":true},{"chunk_id":"ckv9weben2x8l","chunk_label":"unnamed-chunk-13","document_id":"95E990B3","expansion_state":0,"options":{"engine":"r","label":"unnamed-chunk-1"},"row":214,"row_count":1,"visible":true},{"chunk_id":"cxs9myy2fgft4","chunk_label":"unnamed-chunk-14","document_id":"95E990B3","expansion_state":0,"options":{"engine":"r","label":"unnamed-chunk-2"},"row":226,"row_count":1,"visible":true}],"doc_write_time":1517613514}